dataserve/DataContainer.py
dataserve/HTTPDataClient.py
dataserve/HTTPDataServer.py
dataserve/ProxyServer.py
dataserve/__init__.py
dataserve/http_utils.py
dataserve-0.1.0.dist-info/LICENSE
dataserve-0.1.0.dist-info/METADATA
dataserve-0.1.0.dist-info/WHEEL
dataserve-0.1.0.dist-info/top_level.txt
dataserve-0.1.0.dist-info/RECORD
