Metadata-Version: 2.1
Name: dataserve
Version: 0.1.0
Summary: A module for serving up python data in a stand-alone process.
Home-page: https://github.com/bjascob/PythonDataServe
Author: Brad Jascob
Author-email: bjascob@msn.com
License: UNKNOWN
Platform: UNKNOWN
Classifier: Programming Language :: Python :: 3
Classifier: License :: OSI Approved :: MIT License
Classifier: Operating System :: OS Independent
Requires-Dist: requests
